Metadata-Version: 2.1
Name: kubestriker
Version: 1.0.0
Summary: A Blazing fast Security Auditing tool for Kuberentes
Home-page: https://github.com/vchinnipilli/kubestriker
Author: vasant chinnipilli
Author-email: vchinnipilli@gmail.com.com
License: UNKNOWN
Platform: UNKNOWN
Classifier: Programming Language :: Python :: 3
Classifier: License :: OSI Approved :: Apache Software License
Classifier: Operating System :: OS Independent
Requires-Python: >=3.0
Requires-Dist: colorama (==0.4.4)
Requires-Dist: colored (==1.4.2)
Requires-Dist: figlet (==0.0.1)
Requires-Dist: progress (==1.5)
Requires-Dist: prompt-toolkit (==1.0.15)
Requires-Dist: SelectMenu
Requires-Dist: pyfiglet (==0.8.post1)
Requires-Dist: PyYAML (==5.3.1)
Requires-Dist: requests (==2.24.0)
Requires-Dist: urllib3 (==1.25.10)
Requires-Dist: websocket-client (==0.53.0)
